{
  "users": [
    {
      "username": "rushabh",
      "password": "000",
      "friends": [],
      "groups": [],
      "incomingRequests": [],
      "sentRequest": []
    },
    {
      "username": "rama",
      "password": "1971",
      "friends": [],
      "groups": [],
      "incomingRequests": [],
      "sentRequest": []
    },
    {
      "friends": [],
      "groups": [],
      "incomingRequests": [],
      "sentRequest": [
        "rushabh"
      ]
    },
    {
      "friends": [
        "rushabh"
      ],
      "groups": [],
      "incomingRequests": [],
      "sentRequest": []
    }
  ]
}